demo/__init__.py
demo/tests/__init__.py
demo/tests/workflows/__init__.py
demo/tests/workflows/test_diabetes_xgboost.py
demo/tests/workflows/test_sagemaker_xgboost_hpo.py
demo/workflows/__init__.py
demo/workflows/diabetes_sagemaker_xgboost.py
demo/workflows/diabetes_xgboost.py
demo/workflows/sagemaker_xgboost_hpo.py
demo/workflows/sample.py
flytesagemakerplugin/__init__.py
flytesagemakerplugin/sdk/__init__.py
flytesagemakerplugin/sdk/tasks/__init__.py
flytesagemakerplugin/sdk/tasks/plugin.py
gen/__init__.py
gen/pb_python/__init__.py
gen/pb_python/sagemaker_pb2.py
gen/pb_python/sagemaker_pb2_grpc.py
flytesagemakerplugin-0.0.3.dist-info/LICENSE
flytesagemakerplugin-0.0.3.dist-info/METADATA
flytesagemakerplugin-0.0.3.dist-info/WHEEL
flytesagemakerplugin-0.0.3.dist-info/entry_points.txt
flytesagemakerplugin-0.0.3.dist-info/top_level.txt
flytesagemakerplugin-0.0.3.dist-info/RECORD
