Metadata-Version: 2.1
Name: flytesagemakerplugin
Version: 0.0.3
Summary: FlyteKit Example plugin
Home-page: https://github.com/kumare3/awsflyteplugins
Maintainer: AWS + Flyte team
Maintainer-email: ketan.umare@gmail.com
License: apache2
Platform: UNKNOWN
Requires-Python: >=2.7
Requires-Dist: protobuf (!=3.11.*flytekit>=0.6.0,<4,>=3.7.0)
